[
  {
    "id": "demo-01",
    "nombre": { "es": "Producto demo (i18n)", "en": "Demo product (i18n)" },
    "descripcion": {
      "es": "Ejemplo con nombre/descripción traducidos: usa objetos {es,en,...}. Una sola variante (stockInicial como número).",
      "en": "Example with translated name/description: use {es,en,...} objects. Single variant (stockInicial as a number)."
    },
    "precio": 19.90,
    "peso": 300,
    "imgs": [],
    "stockInicial": 10
  },
  {
    "id": "demo-02",
    "nombre": "Producto demo con tallas",
    "descripcion": "Ejemplo con tallas (stockInicial es {talla: cantidad}) y nombre como texto plano. Pon varias rutas en \"imgs\" para ver la galería con miniaturas.",
    "precio": 34.50,
    "peso": 600,
    "imgs": [],
    "stockInicial": { "S": 3, "M": 5, "L": 2 }
  }
]
